odoo/addons/ssi_general_audit/README.rst
odoo/addons/ssi_general_audit/__init__.py
odoo/addons/ssi_general_audit/__manifest__.py
odoo/addons/ssi_general_audit/menu.xml
odoo/addons/ssi_general_audit/data/approval_template_data.xml
odoo/addons/ssi_general_audit/data/general_audit_worksheet_type_category_data.xml
odoo/addons/ssi_general_audit/data/ir_sequence_data.xml
odoo/addons/ssi_general_audit/data/policy_template_data.xml
odoo/addons/ssi_general_audit/data/sequence_template_data.xml
odoo/addons/ssi_general_audit/models/__init__.py
odoo/addons/ssi_general_audit/models/client_account.py
odoo/addons/ssi_general_audit/models/client_account_group.py
odoo/addons/ssi_general_audit/models/client_account_mapping.py
odoo/addons/ssi_general_audit/models/client_account_mapping_detail.py
odoo/addons/ssi_general_audit/models/client_account_type.py
odoo/addons/ssi_general_audit/models/client_account_type_computation_item.py
odoo/addons/ssi_general_audit/models/client_account_type_set.py
odoo/addons/ssi_general_audit/models/client_adjustment_entry.py
odoo/addons/ssi_general_audit/models/client_adjustment_entry_detail.py
odoo/addons/ssi_general_audit/models/client_business_process.py
odoo/addons/ssi_general_audit/models/client_financial_ratio.py
odoo/addons/ssi_general_audit/models/client_trial_balance.py
odoo/addons/ssi_general_audit/models/client_trial_balance_computation.py
odoo/addons/ssi_general_audit/models/client_trial_balance_detail.py
odoo/addons/ssi_general_audit/models/client_trial_balance_group_detail.py
odoo/addons/ssi_general_audit/models/client_trial_balance_standard_detail.py
odoo/addons/ssi_general_audit/models/general_audit.py
odoo/addons/ssi_general_audit/models/general_audit_account_adjustment.py
odoo/addons/ssi_general_audit/models/general_audit_adjustment.py
odoo/addons/ssi_general_audit/models/general_audit_business_environment.py
odoo/addons/ssi_general_audit/models/general_audit_computation.py
odoo/addons/ssi_general_audit/models/general_audit_detail.py
odoo14_addon_ssi_general_audit-14.0.3.1.0.dist-info/METADATA
odoo14_addon_ssi_general_audit-14.0.3.1.0.dist-info/WHEEL
odoo14_addon_ssi_general_audit-14.0.3.1.0.dist-info/top_level.txt
odoo14_addon_ssi_general_audit-14.0.3.1.0.dist-info/RECORD
